hola_mundo/__init__.py
hola_mundo/main.py
hello_world_martin-0.0.1.dist-info/LICENSE
hello_world_martin-0.0.1.dist-info/METADATA
hello_world_martin-0.0.1.dist-info/WHEEL
hello_world_martin-0.0.1.dist-info/top_level.txt
hello_world_martin-0.0.1.dist-info/RECORD
